{
  "id": "1d946aed06755a41c4c36dea329bf366",
  "name": "Monster Girl",
  "native_name": null,
  "full_name": "Catherine",
  "basic_info": {
    "gender": "Female",
    "species": "Human",
    "race": "Human",
    "bloodline": null,
    "height_cm": 165,
    "weight_kg": 55,
    "age": "Teens",
    "birthday": "Unknown",
    "zodiac": "Unknown",
    "blood_type": "Unknown",
    "weight_kkg": null,
    "bmi": 20.2,
    "nationality": null
  },
  "appearance": {
    "eye_color": "Green",
    "hair_color": "Green",
    "skin_color": "Green",
    "notable_features": [
      "Monster form"
    ],
    "skin": "Green",
    "eye": null,
    "hair": null
  },
  "origin": {
    "place_of_birth": "Earth",
    "current_location": "Earth",
    "base_of_operations": "Teen Team HQ",
    "place": null,
    "current": null,
    "base": null
  },
  "occupation": {
    "primary": "Superhero",
    "secondary": "Teen Team",
    "rank_title": "Member",
    "rank": null,
    "rank-title": null
  },
  "affiliations": {
    "current": [
      "Teen Team"
    ],
    "previous": [],
    "relatives": []
  },
  "first_appearance": {
    "anime": "N/A",
    "manga": "Invincible",
    "comics": "Image Comics",
    "game": null
  },
  "abilities": [
    {
      "name": "Monster Transformation",
      "native_name": null,
      "description": "Transform into monster form",
      "type": "Attack",
      "tier": "A",
      "power_level": 80,
      "range": "Melee",
      "limit": "Duration"
    }
  ],
  "signature_moves": [
    "Monster Smash"
  ],
  "ultimate_move": "Full Monster Rampage",
  "power_attributes": {
    "power_type": "Transformation",
    "power_source": "Viltrumite Genetics",
    "combat_style": [
      "Monster combat"
    ],
    "weapon": "Unknown",
    "equipment": [],
    "trump_card": "Monster Transformation",
    "ultimate_move": "Full Monster Rampage"
  },
  "personality": {
    "traits": [
      "Strong",
      "Brave"
    ],
    "likes": [
      "Fighting"
    ],
    "dislikes": [
      "Weakness"
    ],
    "fear": "Not being able to transform",
    "dream": "Help people",
    "personality_type": "ESTJ",
    "Dream": null,
    "alignment": null,
    "strengths": [
      "Brave"
    ],
    "weaknesses": []
  },
  "character": {
    "arc": "Teen hero with monster form",
    "motivation": "Help people",
    "affinity": "Transformation",
    "alignment": "Neutral Good"
  },
  "achievements": [
    "Teen Team member"
  ],
  "titles": [
    "Monster Girl",
    "Catherine"
  ],
  "bounty": {
    "amount": null,
    "currency": "USD",
    "details": "Hero"
  },
  "powerstats": {
    "intelligence": 55,
    "strength": 85,
    "speed": 60,
    "durability": 75,
    "power": 70,
    "combat": 60,
    "total": 405
  },
  "weaknesses": {
    "list": [
      "Duration limit",
      "Transformation trigger"
    ],
    "factors": []
  },
  "relationships": {
    "nemesis": null,
    "allies": [
      "Teen Team"
    ],
    "allies_detailed": [],
    "enemies": [
      "Villains/Antagonists"
    ],
    "enemies_detailed": [],
    "love_interest": null,
    "best_friend": null,
    "rival": null,
    "mentor": null,
    "student": null,
    "leader": null,
    "subordinate": null,
    "acquaintance": null,
    "editor": null,
    "son": null,
    "servant": null,
    "teammate": null,
    "friend": [
      "Teen Team"
    ],
    "colleague": null,
    "enemy": [
      "Villains/Antagonists"
    ],
    "partner": null,
    "father": null,
    "mother": null,
    "adoptive_brother": null,
    "master": null,
    "relatives": [
      "Omni"
    ],
    "grandson": null,
    "girlfriend": null,
    "Stand": null,
    "boss": null,
    "former_leader": null,
    "customer": null,
    "sister": null,
    "commander": null,
    "teacher": null,
    "classmate": null,
    "team": null,
    "ward": null,
    "stand": null,
    "recipient": null,
    "wife": null,
    "employer": null,
    "cousin": null,
    "opponent": null,
    "grandfather": null,
    "brother": null,
    "descendant": null,
    "love": null,
    "successor": null,
    "bandmate": null,
    "captain": null,
    "protects": null,
    "comrades": [],
    "family": [
      "Omni"
    ],
    "daughter": null,
    "subject": null,
    "former crew": null,
    "predecessor": null,
    "lieutenant": null,
    "target": null,
    "host": null,
    "manager": null,
    "ally": null,
    "employee": null,
    "savior": null,
    "sibling": null,
    "nephew": null,
    "victim": null,
    "fiancee": null,
    "tenant": null,
    "apprentice": null,
    "senpai": null,
    "charge": null,
    "clan": null,
    "subordinates": null,
    "husband": null,
    "junior": null,
    "crush": null,
    "nemesa": null,
    "former opponent": null,
    "boyfriend": null,
    "rivals": [],
    "fiance": null,
    "major": null,
    "students": null,
    "guardian": null,
    "band": null,
    "party": null,
    "general": null,
    "twin": null,
    "parents": null,
    "zodiac": null,
    "child": null,
    "niece": null,
    "friends": [
      "Teen Team"
    ],
    "sisters": null,
    "coach": null,
    "gym mates": [],
    "creator": null,
    "servants": [],
    "president": null,
    "grandmother": null,
    "allegiance": null,
    "patient": null,
    "assistant": null,
    "admirer": null,
    "vice-captain": null,
    "squad": null,
    "empress": null,
    "protectors": null,
    "obsession": null,
    "companion": null,
    "crew": null,
    "children": null,
    "senior": null,
    "superior": null,
    "advisor": null,
    "creation": null,
    "father figure": null,
    "former comrade": null,
    "notable_battles": [],
    "mentors": []
  },
  "notable_battles": [],
  "quotes": [
    "Fear me!"
  ],
  "voice_acting": {
    "native_language": "English",
    "english": "Mary McDonnell",
    "note": "Animated series",
    "native_name": null,
    "japanese": "Unknown"
  },
  "story": {
    "status": "Alive",
    "fate": "Continues heroics",
    "transformation": "Monster form",
    "awakening_potential": "Better control",
    "power_evolution": [
      "Novice",
      "Experienced"
    ],
    "role_in_story": "Supporting Character",
    "awakening": null,
    "role": null,
    "face": null,
    "transform": null
  },
  "misc": {
    "transports": [],
    "vehicles": [],
    "headquarters": "Teen Team HQ",
    "story_importance": "Minor",
    "note": null
  },
  "publisher": "image_comics",
  "trump_card": "Monster Transformation",
  "about": "Monster Girl known as a Superhero serving as a supporting character from Image Comics.",
  "note": null,
  "source": "image_comics"
}
