{
  "id": "115c4443a2708aec09f636606847d5e3",
  "name": "Kakashi Hatake",
  "native_name": "트는",
  "full_name": "Kakashi Hatake",
  "basic_info": {
    "gender": "Male",
    "species": "Human",
    "race": "Human",
    "bloodline": "Hatake Clan",
    "height_cm": 181,
    "weight_kg": 72,
    "age": "30-41",
    "birthday": "September 15",
    "zodiac": "Virgo",
    "blood_type": "O",
    "weight_kkg": null,
    "bmi": 22,
    "nationality": null
  },
  "appearance": {
    "eye_color": "Black (Sharingan purple)",
    "hair_color": "Black",
    "skin_color": "Fair",
    "notable_features": [
      "Sharingan eye (left)",
      "Mysterious mask",
      "Dog summon tags",
      "Lazy eyes"
    ],
    "skin": "Fair",
    "eye": null,
    "hair": null
  },
  "origin": {
    "place_of_birth": "Konohagakure",
    "current_location": "Konohagakure",
    "base_of_operations": "Hokage Tower",
    "place": null,
    "current": null,
    "base": null
  },
  "occupation": {
    "primary": "Shinobi",
    "secondary": "Hokage (Sixth)",
    "rank_title": "Sixth Hokage / Captain of Team 7",
    "rank": null,
    "rank-title": null
  },
  "affiliations": {
    "current": [
      "Konohagakure"
    ],
    "previous": [
      "Team Minato",
      "Team 7"
    ],
    "relatives": [
      "Sakumo Hatake (father)"
    ]
  },
  "first_appearance": {
    "anime": "Naruto Episode 1",
    "manga": "Naruto Chapter 1",
    "comics": null,
    "game": null
  },
  "abilities": [
    {
      "name": "Sharingan",
      "native_name": "寫輪眼",
      "description": "Uchiha eye implant granting copy ability, predictive vision, genjutsu. Evolved to Mangekyo.",
      "type": "Support",
      "tier": "S",
      "power_level": 95,
      "range": "Long",
      "limit": "Chakra drain, non-Uchiha body"
    },
    {
      "name": "Mangekyo Sharingan",
      "native_name": "萬花筒寫輪眼",
      "description": "Advanced form with Kamui ability - warp targets to different dimension",
      "type": "Utility",
      "tier": "S+",
      "power_level": 98,
      "range": "Long",
      "limit": "Massive chakra drain"
    },
    {
      "name": "Chidori",
      "native_name": "千鳥",
      "description": "Lightning blade - concentrated lightning chakra in hand for piercing. Named Lightning Cutter for splitting lightning.",
      "type": "Attack",
      "tier": "S",
      "power_level": 95,
      "range": "Short",
      "limit": "Requires Sharingan to use safely"
    },
    {
      "name": "Kamui",
      "native_name": "神威",
      "description": "Mangekyo ability - opens portal to dimension to teleport/self anything",
      "type": "Utility",
      "tier": "S+",
      "power_level": 98,
      "range": "Long",
      "limit": "Heavy chakra drain"
    },
    {
      "name": "Susanoo",
      "native_name": "須佐能乎",
      "description": "Full body armored entity with wings and katana - only used briefly with both eyes",
      "type": "Defense",
      "tier": "S+",
      "power_level": 98,
      "range": "Long",
      "limit": "Requires both Mangekyo eyes"
    },
    {
      "name": "All Nature Transformations",
      "native_name": "所有屬性變化",
      "description": "Master of all five basic nature transformations plus Lightning Release",
      "type": "Attack",
      "tier": "A+",
      "power_level": 80,
      "range": "Various",
      "limit": null
    }
  ],
  "signature_moves": [
    "Chidori",
    "Kamui",
    "Sharingan copy",
    "Lightning Release"
  ],
  "ultimate_move": "Susanoo with Kamui",
  "trump_card": "Full power Kamui + Susanoo combo",
  "power_attributes": {
    "power_type": "Chakra",
    "power_source": "Sharingan + training",
    "combat_style": [
      "Ninjutsu",
      "Lightning jutsu",
      "Sharingan combat"
    ],
    "weapon": "Kunai, chakra blades",
    "equipment": [
      "Chidori",
      "Susanoo"
    ],
    "trump_card": "Full power Kamui + Susanoo combo",
    "ultimate_move": "Susanoo with Kamui"
  },
  "personality": {
    "traits": [
      "Lazy",
      "Pervert",
      "Loyal",
      "Tactical",
      "Caring under facade"
    ],
    "likes": [
      "novels",
      "Dogs",
      "Lazy days",
      "Team 7"
    ],
    "dislikes": [
      "Disrespect",
      "Losing team members"
    ],
    "fear": "Losing those he cares about",
    "dream": "Protect his team and village",
    "personality_type": "INTP",
    "Dream": null,
    "alignment": null,
    "strengths": [
      "Tactical",
      "Loyal"
    ],
    "weaknesses": [
      "Lazy"
    ]
  },
  "character": {
    "arc": "Copy ninja who learned the value of bonds - became Hokage",
    "motivation": "Protecting those important to him",
    "affinity": "Lightning/Sharingan",
    "alignment": "Lawful Good"
  },
  "achievements": [
    "Sixth Hokage",
    "Leader of Team 7",
    "Defeated many powerful enemies",
    "Master of all nature transforms"
  ],
  "titles": [
    "Kakashi of the Sharingan",
    "Copy Ninja",
    "Sixth Hokage",
    "Lazy Shinobi"
  ],
  "bounty": {
    "amount": null,
    "currency": "N/A",
    "details": "Hokage - no bounty"
  },
  "powerstats": {
    "intelligence": 95,
    "strength": 75,
    "speed": 85,
    "durability": 75,
    "power": 95,
    "combat": 95,
    "total": 520
  },
  "weaknesses": {
    "list": [
      "Sharingan chakra drain",
      "Cannot use Susanoo without both eyes"
    ],
    "factors": [
      "lazy"
    ]
  },
  "relationships": {
    "nemesis": "Obito (formerly)",
    "allies": [
      "Team 7",
      "Obito (memory)",
      "Rin"
    ],
    "allies_detailed": [
      {
        "name": "Naruto Uzumaki",
        "relationship": "Student",
        "trust_level": "High"
      },
      {
        "name": "Sasuke Uchiha",
        "relationship": "Student",
        "trust_level": "High"
      },
      {
        "name": "Sakura Haruno",
        "relationship": "Student",
        "trust_level": "Medium"
      },
      {
        "name": "Obito Uchiha",
        "relationship": "Best friend",
        "trust_level": "High - gave eye"
      }
    ],
    "enemies": [
      "Akatsuki",
      "Madara",
      "Kaguya"
    ],
    "enemies_detailed": [],
    "love_interest": "Rin (unrequited)",
    "best_friend": "Obito Uchiha",
    "rival": null,
    "mentor": "Minato Namikaze",
    "student": "Naruto, Sasuke, Sakura",
    "leader": null,
    "subordinate": null,
    "acquaintance": null,
    "editor": null,
    "son": null,
    "servant": null,
    "teammate": null,
    "friend": [
      "Team 7",
      "Obito (memory)",
      "Rin",
      "Obito Uchiha"
    ],
    "colleague": null,
    "enemy": [
      "Obito (formerly)"
    ],
    "partner": null,
    "father": null,
    "mother": null,
    "adoptive_brother": null,
    "master": null,
    "relatives": [],
    "grandson": null,
    "girlfriend": null,
    "Stand": null,
    "boss": null,
    "former_leader": null,
    "customer": null,
    "sister": null,
    "commander": null,
    "teacher": null,
    "classmate": null,
    "team": null,
    "ward": null,
    "stand": null,
    "recipient": null,
    "wife": null,
    "employer": null,
    "cousin": null,
    "opponent": null,
    "grandfather": null,
    "brother": null,
    "descendant": null,
    "love": null,
    "successor": null,
    "bandmate": null,
    "captain": null,
    "protects": null,
    "comrades": [],
    "family": [],
    "daughter": null,
    "subject": null,
    "former crew": null,
    "predecessor": null,
    "lieutenant": null,
    "target": null,
    "host": null,
    "manager": null,
    "ally": null,
    "employee": null,
    "savior": null,
    "sibling": null,
    "nephew": null,
    "victim": null,
    "fiancee": null,
    "tenant": null,
    "apprentice": null,
    "senpai": null,
    "charge": null,
    "clan": null,
    "subordinates": null,
    "husband": null,
    "junior": null,
    "crush": null,
    "nemesa": null,
    "former opponent": null,
    "boyfriend": null,
    "rivals": [],
    "fiance": null,
    "major": null,
    "students": [
      "Naruto, Sasuke, Sakura"
    ],
    "guardian": null,
    "band": null,
    "party": null,
    "general": null,
    "twin": null,
    "parents": null,
    "zodiac": null,
    "child": null,
    "niece": null,
    "friends": [
      "Team 7",
      "Obito",
      "Rin",
      "Obito Uchiha"
    ],
    "sisters": null,
    "coach": null,
    "gym mates": [],
    "creator": null,
    "servants": [],
    "president": null,
    "grandmother": null,
    "allegiance": null,
    "patient": null,
    "assistant": null,
    "admirer": null,
    "vice-captain": null,
    "squad": null,
    "empress": null,
    "protectors": null,
    "obsession": null,
    "companion": null,
    "crew": null,
    "children": null,
    "senior": null,
    "superior": null,
    "advisor": null,
    "creation": null,
    "father figure": null,
    "former comrade": null,
    "notable_battles": [],
    "mentors": [
      "Minato Namikaze"
    ]
  },
  "notable_battles": [
    {
      "opponent": "Zabuza",
      "result": "Victory",
      "method": "Sharingan copied water jutsu"
    },
    {
      "opponent": "Deidara",
      "result": "Victory",
      "method": "Kamui warped arm"
    },
    {
      "opponent": "Obito/Madara",
      "result": "Victory (war)",
      "method": "Combined efforts"
    }
  ],
  "quotes": [
    "Those who break the rules are trash... but those who abandon their allies are worse than trash!",
    "I am kakashi hatake... and I like it just fine.",
    "In the ninja world, those who break the rules are trash... but that doesn't exception me!"
  ],
  "voice_acting": {
    "native_language": "Tosiyuki P (Japanese)",
    "note": "Actually: Japanese: 'Toshiyuki Hosoi / Kenji (Japanese)', 'Willem S.' wrong - real: 'Cannon (pervert)'",
    "native_name": null,
    "english": "Dave Wittenberg",
    "japanese": "Kazuhiko Inoue"
  },
  "story": {
    "status": "Alive",
    "fate": "Serving as Hokage",
    "transformation": "Mangekyo Sharingan",
    "awakening_potential": "Eternal Mangekyo (if Uchiha)",
    "power_evolution": [
      "Prodigy",
      "Copy ninja",
      "Mangekyo user",
      "Hokage"
    ],
    "role_in_story": "Major Supporting Character",
    "awakening": null,
    "role": null,
    "face": null,
    "transform": null
  },
  "misc": {
    "transports": [],
    "vehicles": [],
    "headquarters": "Hokage Tower",
    "story_importance": "Major",
    "note": null
  },
  "publisher": "anime",
  "about": "Age: 26–27 (Part I); 29–31 (Part II)\nBirthday: September 15\nHoroscope: Virgo\nBlood type: O\nHeight: 5\"11\"\nWeight: 67.5 kg \nHair: Silver\nEyes: Grey, Sharingan\nRank: Jonin, Former ANBU, \nLikes: Icha-Icha series, Broiled Saury with salt, Miso soup with eggplant\nDislikes: Anything sweet\nQuote: (from Obito) \"A shinobi who violates the rules is scum, but a shinobi who abandons their friends is worse than scum.\"\n\nMajor Background Spoilers\n\nKakashi has an ongoing, albeit slightly one-sided, rivalry with Might Guy, with Guy constantly proclaiming that Kakashi is his rival, and considering his and Kakashi's subordinates rivals. Kakashi, however, seems indifferent to their rivalry, which annoys Guy to no end. Guy randomly challenges Kakashi to contests of skill, and Kakashi has acquired a record of 49 wins and 50 losses in doing so. Given that the contests that make up this figure are so varied (ranging from Rock, Paper, Scissors to sumo-wrestling), this is not much of an achievement on Guy's part. Nevertheless, Guy is proud of his record.\n\nThough he evasively says that he has \"many hobbies\" when asked about himself, he is commonly seen reading of \"Icha Icha Paradise\" (イチャイチャパラダイス, Icha Icha Paradaisu, literally \"Make Out Paradise\"), an adult and probably pornographic novel authored by Jiraiya that is a runaway bestseller in the Naruto world. Kakashi most prominently reads it while training and speaking with his team, and is later seen reading the second known volume in the series, \"Icha Icha Violence\" (イチャイチャバイオレンス, Icha Icha Baiorensu, literally \"Make Out Violence\"). In Part II Naruto gives him the new \"Icha Icha Tactics\" (イチャイチャタクティクス, Icha Icha Takutikusu, literally \"Make Out Tactics\").\n\nKakashi's Sharingan eye gives him a significant advantage in battle, as he can copy enemy techniques and use them as his own, as well as track and predict his opponent's movements flawlessly. Because it is a transplanted eye, his Sharingan eye is always active. While this would not be much of a problem for an Uchiha, his non-Uchiha blood causes it to use much more chakra than it should. Because of this, he covers it with his headband and only utilizes it in the most dangerous battles. Kakashi's use of the Sharingan is as good as that of Itachi Uchiha, though the aforementioned handicaps brought about by the nature of his eye make him somewhat weaker in comparison. In Part II Kakashi is able to develop his own Mangekyo Sharingan. With his variant he is able to manipulate space-time to conduct long range attacks, and in its two uses has been capable of severing another's arms and otherwise sending things to different dimensions. Much like the standard Sharingan, the Mangekyo Sharingan tires Kakashi considerably, and after using it only three times he was hospitalized for a week due to its chakra usage.\n\nWith his Sharingan Kakashi has been able to copy more than one thousand jutsu, giving him the nickname \"Copy Ninja Kakashi\". As a result, Kakashi's arsenal most prominently features ninjutsu abilities and has led to him becoming a specialist in the field. Many of the jutsu he has been seen copying in the series are water-based attacks, though most of these he only uses against the person he copies them from. He does, however, use Water Release: Water Encampment Wall on occasion as a way to block attacks. He less frequently uses other elemental attacks such as Fire Release: Great Fireball Technique to attack opponents or Earth Release: Inner Decapitation Technique (土遁・心中斬首の術, Doton: Shinjū Zanshu no Jutsu, Viz \"Groundhog Technique Decapitation\", English TV \"Headhunter Jutsu\") to pull opponents below ground and immobilize them. He can also create shadow clones, though because he lacks Naruto's chakra reserves, he exercises the ability with caution, rarely creating more than one at a time.\n\nWhile Kakashi specializes in the use of ninjutsu due to his Sharingan he is fairly adept with other jutsu types, though his use of them is rarely seen. Demonic Illusion: Hell Viewing Technique (魔幻・奈烙見の術, Magen: Narakumi no Jutsu) causes his opponent to see what they would find a horrifying vision, keeping them preoccupied until they can overcome the illusion. A Thousand Years of Pain (death in english dub) (千年殺し, Sennen Goroshi) consists of Kakashi forcefully plunging his index and middle fingers into an opponent's rectum. While only capable of launching the opponent humorous distances in typical uses, the fingers can be replaced with kunai attached with exploding tags to actually do damage to the person one is attacking.\n\nWhen he was younger, Kakashi was taught how to use the Rasengan by the Fourth Hokage. Because the Rasengan is meant to have the user's chakra nature mixed with it, Kakashi attempted to add his lightning-based chakra to it, though was ultimately unsuccessful. In time he instead created the Chidori, his only original jutsu. After the jutsu's initial creation, Kakashi was unable to use the Chidori to its full potential as the sheer speed of the attack left his normal eyes unable to see any form of an enemy counterattack. After acquiring the Sharingan, however, he was able to overcome this shortcoming. Through repeated use and increased proficiency with it, Kakashi's Chidori has been upgraded and renamed to the Lightning Blade due to him having cut through a bolt of lightning with it.",
  "note": null,
  "source": "anime"
}
